ckanext_dcor_schemas-1.1.1-py3.12-nspkg.pth
ckanext/dcor_schemas/__init__.py
ckanext/dcor_schemas/_version.py
ckanext/dcor_schemas/actions.py
ckanext/dcor_schemas/auth.py
ckanext/dcor_schemas/cli.py
ckanext/dcor_schemas/helpers.py
ckanext/dcor_schemas/jobs.py
ckanext/dcor_schemas/licenses.json
ckanext/dcor_schemas/licenses_medical.json
ckanext/dcor_schemas/plugin.py
ckanext/dcor_schemas/signals.py
ckanext/dcor_schemas/validate.py
ckanext/dcor_schemas/assets/hide_for_non_admin.css
ckanext/dcor_schemas/assets/hide_unused_elements.css
ckanext/dcor_schemas/assets/webassets.yml
ckanext/dcor_schemas/resource_schema_supplements/__init__.py
ckanext/dcor_schemas/resource_schema_supplements/supplement1_general.json
ckanext/dcor_schemas/resource_schema_supplements/supplement2_cells.json
ckanext/dcor_schemas/resource_schema_supplements/supplement3_artificial.json
ckanext/dcor_schemas/resource_schema_supplements/supplement4_chip.json
ckanext/dcor_schemas/resource_schema_supplements/supplement5_experiment.json
ckanext/dcor_schemas/resource_schema_supplements/supplement6_identifiers.json
ckanext/dcor_schemas/templates/.gitignore
ckanext/dcor_schemas/templates/base.html
ckanext/dcor_schemas/templates/home/snippets/featured_group.html
ckanext/dcor_schemas/templates/home/snippets/featured_organization.html
ckanext/dcor_schemas/templates/package/edit_base.html
ckanext/dcor_schemas/templates/package/resource_read.html
ckanext/dcor_schemas/templates/package/resources.html
ckanext/dcor_schemas/templates/package/snippets/additional_info.html
ckanext/dcor_schemas/templates/package/snippets/package_basic_fields.html
ckanext/dcor_schemas/templates/package/snippets/package_metadata_fields.html
ckanext/dcor_schemas/tests/__init__.py
ckanext/dcor_schemas/tests/requirements.txt
ckanext/dcor_schemas/tests/test_action_resource_upload_s3.py
ckanext/dcor_schemas/tests/test_actions.py
ckanext/dcor_schemas/tests/test_auth_dataset.py
ckanext/dcor_schemas/tests/test_auth_group.py
ckanext_dcor_schemas-1.1.1.dist-info/licenses/LICENSE
ckanext_dcor_schemas-1.1.1.dist-info/METADATA
ckanext_dcor_schemas-1.1.1.dist-info/WHEEL
ckanext_dcor_schemas-1.1.1.dist-info/entry_points.txt
ckanext_dcor_schemas-1.1.1.dist-info/namespace_packages.txt
ckanext_dcor_schemas-1.1.1.dist-info/top_level.txt
ckanext_dcor_schemas-1.1.1.dist-info/RECORD
