Metadata-Version: 2.4
Name: ckanext-dcor_schemas
Version: 1.1.1
Summary: Introduces or lifts restrictions (authorization) for managing data and metadata on DCOR
Author: Paul Müller
Maintainer-email: Paul Müller <dev@craban.de>
License: GNU Affero General Public License v3 or later (AGPLv3+)
Project-URL: source, https://github.com/DCOR-dev/ckanext-dcor_schemas
Project-URL: tracker, https://github.com/DCOR-dev/ckanext-dcor_schemas/issues
Project-URL: changelog, https://github.com/DCOR-dev/ckanext-dcor_schemas/blob/main/CHANGELOG
Keywords: DC,DCOR,deformability,cytometry
Classifier: Operating System :: OS Independent
Classifier: Programming Language :: Python :: 3
Classifier: Topic :: Scientific/Engineering :: Visualization
Classifier: Intended Audience :: Science/Research
Requires-Python: <4,>=3.8
License-File: LICENSE
Requires-Dist: ckan<3,>=2.10.4
Requires-Dist: dclab>=0.60.9
Requires-Dist: dcor_shared>=0.10.0
Requires-Dist: python-slugify
Requires-Dist: rq<2,>=1.10
Dynamic: license-file
